<?xml version="1.0" encoding="utf-8" ?>
<dwsync>
<file name="SharePointMenu.css" server="Z:/" local="130354302910000000" remote="130365350430000000" Dst="1" />
<file name="DepartmentLinks.css" server="Z:/" local="130354301380000000" remote="130365350220000000" Dst="1" />
<file name="ExploreDropdown.css" server="Z:/" local="130354301500000000" remote="130365350230000000" Dst="1" />
<file name="Footer.css" server="Z:/" local="130354301630000000" remote="130365350250000000" Dst="1" />
<file name="Header.css" server="Z:/" local="130354301870000000" remote="130365350270000000" Dst="1" />
<file name="LeftNavigation.css" server="Z:/" local="130354302380000000" remote="130365350350000000" Dst="1" />
<file name="Main.css" server="Z:/" local="130354302530000000" remote="130365350360000000" Dst="1" />
<file name="Breadcrumbs.css" server="Z:/" local="130354301170000000" remote="130365350160000000" Dst="1" />
<file name="UtilityLinks.css" server="Z:/" local="130354303530000000" remote="130365350590000000" Dst="1" />
<file name="SiteMap.css" server="Z:/" local="130354303020000000" remote="130365350450000000" Dst="1" />
<file name="core.css" server="Z:/" local="130362899750000000" remote="130365350200000000" Dst="1" />
<file name="common.css" server="Z:/" local="130362879400000000" remote="130365350180000000" Dst="1" />
<file name="TableLayoutcss.css" server="Z:/" local="130362899330000000" remote="130365350460000000" Dst="1" />
<file name="GlobalNavigation.css" server="Z:/" local="130365279190000000" remote="130365350260000000" Dst="1" />
<file name="Search.css" server="Z:/" local="130354302770000000" remote="130365350420000000" Dst="1" />
<file name="TwoColumnLayout.css" server="Z:/" local="130354303330000000" remote="130365350520000000" Dst="1" />
<file name="JqueryTabs.css" server="Z:/" local="130354302240000000" remote="130365350310000000" Dst="1" />
<file name="WelcomeDeptPediatrics.css" server="Z:/" local="130354303630000000" remote="130365350610000000" Dst="1" />
<file name="JQuerySlides.css" server="Z:/" local="130354302110000000" remote="130365350300000000" Dst="1" />
<file name="ThreeColumnLayout.css" server="Z:/" local="130354303240000000" remote="130365350510000000" Dst="1" />
<file name="WelcomeDivisionPediatrics.css" server="Z:/" local="130354303770000000" remote="130365350620000000" Dst="1" />
<file name="WelcomePediatrics.css" server="Z:/" local="130354304150000000" remote="130365350660000000" Dst="1" />
<file name="AccordionArrowOnly_3col.css" server="Z:/" local="130354301030000000" remote="130365350150000000" Dst="1" />
<file name="WelcomeLab3Column.css" server="Z:/" local="130354303980000000" remote="130365350650000000" Dst="1" />
<file name="Radmenu.css" server="Z:/" local="130362900280000000" remote="130365350400000000" Dst="1" />
<file name="Print.css" server="Z:/" local="130354302670000000" remote="130365350390000000" Dst="1" />
<file name="AccordionArrowOnly.css" server="Z:/" local="130354300880000000" remote="130365350140000000" Dst="1" />
<file name="TabsAZ.css" server="Z:/" local="130354303140000000" remote="130365350490000000" Dst="1" />
<file name="ie6.css" server="Z:/" local="130354301980000000" remote="130365350280000000" Dst="1" />
<file name="WelcomeLab.css" server="Z:/" local="130354303870000000" remote="130365350630000000" Dst="1" />
<file name="Layout.html" server="Z:/" local="130362937640000000" remote="130365350320000000" Dst="1" />
<file name="NewPediatrics.html" server="Z:/" local="130362118300000000" remote="130365350380000000" Dst="1" />
</dwsync>