<?xml version="1.0" encoding="utf-8" ?>
<dwsync>
<file name="OneColumn_01.png" server="Z:/" local="130362138660000000" remote="130365348540000000" Dst="1" />
<file name="spacer.gif" server="Z:/" local="130362138860000000" remote="130365348830000000" Dst="1" />
<file name="OneColumn_02.png" server="Z:/" local="130362138670000000" remote="130365348550000000" Dst="1" />
<file name="OneColumn_03.png" server="Z:/" local="130362138690000000" remote="130365348570000000" Dst="1" />
<file name="OneColumn_05.png" server="Z:/" local="130362138720000000" remote="130365348600000000" Dst="1" />
<file name="OneColumn_07.png" server="Z:/" local="130362138750000000" remote="130365348710000000" Dst="1" />
<file name="OneColumn_09.png" server="Z:/" local="130362138780000000" remote="130365348740000000" Dst="1" />
<file name="OneColumn_10.png" server="Z:/" local="130362138790000000" remote="130365348750000000" Dst="1" />
<file name="OneColumn_11.png" server="Z:/" local="130362138810000000" remote="130365348770000000" Dst="1" />
<file name="OneColumn_12.png" server="Z:/" local="130362138820000000" remote="130365348780000000" Dst="1" />
<file name="OneColumn_13.png" server="Z:/" local="130362138830000000" remote="130365348800000000" Dst="1" />
<file name="OneColumn_14.png" server="Z:/" local="130362138850000000" remote="130365348810000000" Dst="1" />
<file name="OneColumn_04.png" server="Z:/" local="130362138710000000" remote="130365348590000000" Dst="1" />
<file name="OneColumn_06.png" server="Z:/" local="130362138740000000" remote="130365348620000000" Dst="1" />
<file name="OneColumn_08.png" server="Z:/" local="130362138770000000" remote="130365348720000000" Dst="1" />
</dwsync>